{"nm":"Main Scene","ddd":0,"h":1000,"w":1000,"meta":{"g":"@lottiefiles/creator 1.64.0"},"layers":[{"ty":0,"nm":"Batteryringplain","sr":1,"st":0,"op":150,"ip":0,"hd":false,"ddd":0,"bm":0,"hasMask":false,"ao":0,"ks":{"a":{"a":0,"k":[500.0000786774104,500.00000465248996]},"s":{"a":0,"k":[100,100]},"sk":{"a":0,"k":0},"p":{"a":0,"k":[500.0000786774104,500.00000465248996]},"r":{"a":0,"k":0},"sa":{"a":0,"k":0},"o":{"a":0,"k":100}},"w":1000,"h":1000,"refId":"precomp_Shape Layer - SVG_XQHcnGAnQ3_398a50eb-28a4-420a-89e6-95b7905bd065","ind":1}],"v":"5.7.0","fr":30,"op":150,"ip":0,"assets":[{"nm":"Batteryringplain","id":"precomp_Shape Layer - SVG_XQHcnGAnQ3_398a50eb-28a4-420a-89e6-95b7905bd065","layers":[{"ty":4,"nm":"layer1","sr":1,"st":0,"op":150,"ip":0,"hd":false,"ddd":0,"bm":0,"hasMask":false,"ao":0,"ks":{"a":{"a":0,"k":[500.0000786774104,500.00000465248996]},"s":{"a":0,"k":[100,100]},"sk":{"a":0,"k":0},"p":{"a":0,"k":[500.0001944799124,500.00004807842816]},"r":{"a":0,"k":0},"sa":{"a":0,"k":0},"o":{"a":0,"k":100}},"shapes":[{"ty":"gr","bm":0,"hd":false,"nm":"circle5","np":2,"it":[{"ty":"sh","bm":0,"hd":false,"nm":"Path 1","d":1,"ks":{"a":0,"k":{"c":true,"i":[[0,0],[85.28,-85.28],[120.61,0],[85.28,85.28],[0,120.61],[-85.28,85.28],[-120.61,0],[-85.28,-85.28],[0,-120.61]],"o":[[0,120.61],[-85.28,85.28],[-120.61,0],[-85.28,-85.28],[0,-120.61],[85.28,-85.28],[120.61,0],[85.28,85.28],[0,0]],"v":[[954.75,500],[821.56,821.56],[500,954.75],[178.44,821.56],[45.25,500],[178.44,178.44],[500,45.25],[821.56,178.44],[954.75,500]]}}},{"ty":"st","bm":0,"hd":false,"nm":"Stroke","lc":2,"lj":2,"ml":4,"o":{"a":0,"k":100},"w":{"a":0,"k":82.37},"c":{"a":0,"k":[0,1,0.4]}},{"ty":"tm","bm":0,"hd":false,"nm":"Trim Path","e":{"a":0,"k":100},"o":{"a":0,"k":275},"s":{"a":1,"k":[{"o":{"x":0.167,"y":0.167},"i":{"x":0.833,"y":0.833},"s":[100],"t":11},{"s":[0],"t":48}]},"m":1},{"ty":"tr","a":{"a":0,"k":[499.9856835091004,499.99096230937084]},"s":{"a":0,"k":[100,100]},"sk":{"a":0,"k":0},"p":{"a":0,"k":[499.9856835091004,499.99096230937084]},"r":{"a":0,"k":0},"sa":{"a":0,"k":0},"o":{"a":1,"k":[{"o":{"x":0.167,"y":0.167},"i":{"x":0.833,"y":0.833},"s":[0],"t":0},{"o":{"x":0.167,"y":0.167},"i":{"x":0.833,"y":0.833},"s":[30],"t":12},{"o":{"x":0.167,"y":0.167},"i":{"x":0.833,"y":0.833},"s":[40],"t":28},{"o":{"x":0.167,"y":0.167},"i":{"x":0.833,"y":0.833},"s":[60],"t":37},{"s":[90],"t":47}]}}]},{"ty":"gr","bm":0,"hd":false,"nm":"text2","np":2,"it":[{"ty":"sh","bm":0,"hd":false,"nm":"Path 2","d":1,"ks":{"a":0,"k":{"c":true,"i":[[0,0],[-4.88,10.35],[0,0],[0,0],[0,0],[-4.75,8.31],[0,1.19],[-65.26,115.09],[2.21,-10.52],[0,0],[0,0],[0,0],[2.37,-4.75],[0,0],[13.2,-23.67],[0,0]],"o":[[-3.81,11.76],[0,0],[0,0],[0,0],[-14.24,0],[4.75,-9.49],[33.22,-58.14],[7.08,-16.78],[0,0],[0,0],[0,0],[11.87,0],[0,0],[-84.64,146.38],[-2.53,4.53],[0,0]],"v":[[474.9,728.84],[448.8,728.84],[449.92,721.24],[474.9,552.05],[385.91,552.05],[376.42,535.44],[377.61,531.88],[524.74,273.23],[550.84,273.23],[549.96,279.21],[524.74,450.02],[613.72,450.02],[625.59,463.07],[624.4,466.63],[478.69,722.04],[474.9,728.84]]}}},{"ty":"st","bm":0,"hd":false,"nm":"Stroke","lc":2,"lj":2,"ml":4,"o":{"a":0,"k":100},"w":{"a":0,"k":25},"c":{"a":0,"k":[0,1,0.4]}},{"ty":"tm","bm":0,"hd":false,"nm":"Trim Path","e":{"a":0,"k":100},"o":{"a":0,"k":0},"s":{"a":1,"k":[{"o":{"x":0.167,"y":0.167},"i":{"x":0.833,"y":0.833},"s":[100],"t":14},{"s":[0],"t":66}]},"m":1},{"ty":"tr","a":{"a":0,"k":[499.9650383377426,499.8361235241874]},"s":{"a":0,"k":[100,100]},"sk":{"a":0,"k":0},"p":{"a":0,"k":[499.9650383377426,499.8361235241874]},"r":{"a":0,"k":0},"sa":{"a":0,"k":0},"o":{"a":0,"k":100}}]},{"ty":"gr","bm":0,"hd":false,"nm":"Group 1","np":2,"it":[{"ty":"gr","bm":0,"hd":false,"nm":"path5","np":2,"it":[{"ty":"sh","bm":0,"hd":false,"nm":"Path 3","d":1,"ks":{"a":0,"k":{"c":true,"i":[[0,0],[-4.88,10.35],[0,0],[0,0],[0,0],[-4.75,8.31],[0,1.19],[-65.26,115.09],[2.21,-10.52],[0,0],[0,0],[0,0],[2.37,-4.75],[0,0],[13.2,-23.67],[0,0]],"o":[[-3.81,11.76],[0,0],[0,0],[0,0],[-14.24,0],[4.75,-9.49],[33.22,-58.14],[7.08,-16.78],[0,0],[0,0],[0,0],[11.87,0],[0,0],[-84.64,146.38],[-2.53,4.53],[0,0]],"v":[[474.9,728.84],[448.8,728.84],[449.92,721.24],[474.9,552.05],[385.91,552.05],[376.42,535.44],[377.61,531.88],[524.74,273.23],[550.84,273.23],[549.96,279.21],[524.74,450.02],[613.72,450.02],[625.59,463.07],[624.4,466.63],[478.69,722.04],[474.9,728.84]]}}},{"ty":"fl","bm":0,"hd":false,"nm":"Fill","c":{"a":0,"k":[0,1,0]},"r":1,"o":{"a":0,"k":100}},{"ty":"tr","a":{"a":0,"k":[499.99721577278854,500.00051876564385]},"s":{"a":0,"k":[100,100]},"sk":{"a":0,"k":0},"p":{"a":0,"k":[499.99721577278854,500.00051876564385]},"r":{"a":0,"k":0},"sa":{"a":0,"k":0},"o":{"a":0,"k":100}}]},{"ty":"tr","a":{"a":0,"k":[499.99721577278854,500.00051876564385]},"s":{"a":1,"k":[{"o":{"x":0.167,"y":0.167},"i":{"x":0.833,"y":0.833},"s":[12.29532772600807,12.295327726008066],"t":0},{"s":[95.71944474168421,95.71944474168434],"t":6}]},"sk":{"a":0,"k":0},"p":{"a":0,"k":[499.99721577278854,500.00051876564385]},"r":{"a":0,"k":0},"sa":{"a":0,"k":0},"o":{"a":1,"k":[{"o":{"x":0.167,"y":0.167},"i":{"x":0.833,"y":0.833},"s":[0],"t":0},{"o":{"x":0.167,"y":0.167},"i":{"x":0.833,"y":0.833},"s":[30],"t":6},{"o":{"x":0.167,"y":0.167},"i":{"x":0.833,"y":0.833},"s":[30],"t":48},{"o":{"x":0.167,"y":0.167},"i":{"x":0.833,"y":0.833},"s":[70],"t":56},{"s":[30],"t":62}]}}]},{"ty":"gr","bm":0,"hd":false,"nm":"circle3","np":2,"it":[{"ty":"sh","bm":0,"hd":false,"nm":"Path 4","d":1,"ks":{"a":0,"k":{"c":true,"i":[[0,0],[77.64,-77.64],[109.8,0],[77.64,77.64],[0,109.8],[-77.64,77.64],[-109.8,0],[-77.64,-77.64],[0,-109.8]],"o":[[0,109.8],[-77.64,77.64],[-109.8,0],[-77.64,-77.64],[0,-109.8],[77.64,-77.64],[109.8,0],[77.64,77.64],[0,0]],"v":[[914,500],[792.75,792.75],[500,914],[207.25,792.75],[85.99,500],[207.25,207.25],[500,85.99],[792.75,207.25],[914,500]]}}},{"ty":"fl","bm":0,"hd":false,"nm":"Fill","c":{"a":0,"k":[0,0,0]},"r":1,"o":{"a":0,"k":100}},{"ty":"tr","a":{"a":0,"k":[499.99503835237186,499.99503489200197]},"s":{"a":1,"k":[{"o":{"x":0.167,"y":0.167},"i":{"x":0.833,"y":0.833},"s":[15.504374438784346,15.504374438784346],"t":0},{"s":[99.99999999999997,99.99999999999997],"t":30}]},"sk":{"a":0,"k":0},"p":{"a":0,"k":[499.99503835237186,499.99503489200197]},"r":{"a":0,"k":0},"sa":{"a":0,"k":0},"o":{"a":1,"k":[{"o":{"x":0.167,"y":0.167},"i":{"x":0.833,"y":0.833},"s":[0],"t":0},{"s":[80],"t":12}]}}]},{"ty":"gr","bm":0,"hd":false,"nm":"Group 2","np":2,"it":[{"ty":"gr","bm":0,"hd":false,"nm":"path3","np":2,"it":[{"ty":"sh","bm":0,"hd":false,"nm":"Path 5","d":1,"ks":{"a":0,"k":{"c":true,"i":[[0,0],[93.77,-93.77],[132.61,0],[93.77,93.77],[0,132.61],[-93.77,93.77],[-132.61,0],[-93.77,-93.77],[0,-132.61]],"o":[[0,132.61],[-93.77,93.77],[-132.61,0],[-93.77,-93.77],[0,-132.61],[93.77,-93.77],[132.61,0],[93.77,93.77],[0,0]],"v":[[1000,500],[853.55,853.55],[500,1000],[146.45,853.55],[0,500],[146.45,146.45],[500,0],[853.55,146.45],[1000,500]]}}},{"ty":"fl","bm":0,"hd":false,"nm":"Fill","c":{"a":0,"k":[1,1,1]},"r":1,"o":{"a":1,"k":[{"o":{"x":0.167,"y":0.167},"i":{"x":0.833,"y":0.833},"s":[0],"t":0},{"s":[100],"t":11}]}},{"ty":"tr","a":{"a":0,"k":[500.0000786774104,500.00000465248996]},"s":{"a":0,"k":[100,100]},"sk":{"a":0,"k":0},"p":{"a":0,"k":[500.0000786774104,500.00000465248996]},"r":{"a":0,"k":0},"sa":{"a":0,"k":0},"o":{"a":0,"k":100}}]},{"ty":"tr","a":{"a":0,"k":[500.0000786774104,500.00000465248996]},"s":{"a":0,"k":[100,100]},"sk":{"a":0,"k":0},"p":{"a":0,"k":[500.0000786774104,500.00000465248996]},"r":{"a":0,"k":0},"sa":{"a":0,"k":0},"o":{"a":0,"k":40}}]}],"ind":1}]}]}